{
  "46588a09-403b-4c59-8f51-580ebb659bb7": {
    "id": "46588a09-403b-4c59-8f51-580ebb659bb7",
    "user_id": "frontend_user",
    "child_id": "frontend_user_child_0",
    "child_name": "日佳梨",
    "date": "2025-06-24",
    "age_in_months": 22,
    "type": "social_skills",
    "category": "playing_together",
    "title": "初めて保育園で友達と手を繋いだ！",
    "description": "ませてしまって悲しいけど、おとなになって嬉しいよ、パパ。",
    "value": null,
    "unit": null,
    "image_url": null,
    "detected_by": "parent",
    "confidence": null,
    "emotions": null,
    "development_stage": null,
    "created_at": "2025-06-24T18:09:15.408138",
    "updated_at": "2025-06-24T18:09:15.408157"
  },
  "8fc95264-9da2-423d-9fa5-038ec22aa950": {
    "id": "8fc95264-9da2-423d-9fa5-038ec22aa950",
    "user_id": "frontend_user",
    "child_id": "frontend_user_child_0",
    "child_name": "日佳梨",
    "date": "2025-06-11",
    "age_in_months": 22,
    "type": "body_growth",
    "category": "height",
    "title": "身長が前回より2cm伸びてた！",
    "description": "もう立派な子どもだね〜",
    "value": null,
    "unit": null,
    "image_url": null,
    "detected_by": "parent",
    "confidence": null,
    "emotions": null,
    "development_stage": null,
    "created_at": "2025-06-24T18:10:38.618427",
    "updated_at": "2025-06-24T18:10:38.618470"
  }
}